eldengym/__init__.py
eldengym/arena_boundary.py
eldengym/env.py
eldengym/envs.py
eldengym/registry.py
eldengym/rewards.py
eldengym/utils.py
eldengym/wrappers.py
eldengym/client/__init__.py
eldengym/client/elden_client.py
eldengym/files/Margit-v0/er_siphon_config.toml
eldengym/files/Margit-v0/keybinds.json
eldengym/files/Margit-v0/keybinds_v2.json
eldengym-0.6.0.dist-info/METADATA
eldengym-0.6.0.dist-info/WHEEL
eldengym-0.6.0.dist-info/licenses/LICENSE
eldengym-0.6.0.dist-info/RECORD
