Metadata-Version: 2.4
Name: eldengym
Version: 0.6.0
Summary: A Gymnasium-compatible reinforcement learning environment for Elden Ring
Project-URL: Homepage, https://eldengym.dhmnr.sh/
Project-URL: Documentation, https://eldengym.dhmnr.sh/
Project-URL: Repository, https://github.com/dhmnr/eldengym
Project-URL: Issues, https://github.com/dhmnr/eldengym/issues
Author-email: dhmnr <mail@dhmnr.sh>
License: MIT
License-File: LICENSE
Keywords: deep-learning,elden-ring,game-ai,gymnasium,reinforcement-learning
Classifier: Development Status :: 3 - Alpha
Classifier: Intended Audience :: Developers
Classifier: Intended Audience :: Science/Research
Classifier: License :: OSI Approved :: MIT License
Classifier: Programming Language :: Python :: 3
Classifier: Programming Language :: Python :: 3.10
Classifier: Programming Language :: Python :: 3.11
Classifier: Programming Language :: Python :: 3.12
Classifier: Topic :: Games/Entertainment
Classifier: Topic :: Scientific/Engineering :: Artificial Intelligence
Requires-Python: >=3.10
Requires-Dist: anthropic>=0.69.0
Requires-Dist: gymnasium>=1.2.1
Requires-Dist: ipykernel>=6.30.1
Requires-Dist: matplotlib>=3.10.7
Requires-Dist: numpy>=2.2.6
Requires-Dist: opencv-python>=4.11.0.86
Requires-Dist: pillow>=11.3.0
Requires-Dist: pysiphon>=1.2.0
